README.md
setup.py
qth_darksky/__init__.py
qth_darksky/version.py
qth_darksky.egg-info/PKG-INFO
qth_darksky.egg-info/SOURCES.txt
qth_darksky.egg-info/dependency_links.txt
qth_darksky.egg-info/entry_points.txt
qth_darksky.egg-info/requires.txt
qth_darksky.egg-info/top_level.txt